openmsitoolbox/__init__.py
openmsitoolbox/version.py
openmsitoolbox/argument_parsing/__init__.py
openmsitoolbox/argument_parsing/has_argument_parser.py
openmsitoolbox/argument_parsing/has_arguments.py
openmsitoolbox/argument_parsing/openmsi_argument_parser.py
openmsitoolbox/argument_parsing/parser_callbacks.py
openmsitoolbox/controlled_process/__init__.py
openmsitoolbox/controlled_process/controlled_process.py
openmsitoolbox/controlled_process/controlled_process_async.py
openmsitoolbox/controlled_process/controlled_process_multi_threaded.py
openmsitoolbox/controlled_process/controlled_process_single_thread.py
openmsitoolbox/logging/__init__.py
openmsitoolbox/logging/formatter.py
openmsitoolbox/logging/log_owner.py
openmsitoolbox/logging/openmsi_logger.py
openmsitoolbox/runnable/__init__.py
openmsitoolbox/runnable/runnable.py
openmsitoolbox/testing/__init__.py
openmsitoolbox/testing/config.py
openmsitoolbox/testing/test_with_logger.py
openmsitoolbox/testing/test_with_output_location.py
openmsitoolbox/utilities/__init__.py
openmsitoolbox/utilities/exception_tracking_thread.py
openmsitoolbox/utilities/misc.py
openmsitoolbox-1.2.4.post1.dist-info/LICENSE
openmsitoolbox-1.2.4.post1.dist-info/METADATA
openmsitoolbox-1.2.4.post1.dist-info/WHEEL
openmsitoolbox-1.2.4.post1.dist-info/top_level.txt
openmsitoolbox-1.2.4.post1.dist-info/RECORD
