Metadata-Version: 2.1
Name: openmsitoolbox
Version: 1.2.4.post1
Summary: Python utilities for OpenMSI projects Developed for Open MSI (NSF DMREF award #1921959)
Home-page: https://github.com/openmsi/openmsitoolbox
Author: OpenMSI Dev Team
Author-email: openmsistream@gmail.com
License: GNU GPLv3
Download-URL: https://github.com/openmsi/openmsitoolbox/archive/refs/tags/v1.2.4post1.tar.gz
Keywords: materials,data_science
Platform: UNKNOWN
Classifier: Programming Language :: Python :: 3.7
Classifier: License :: OSI Approved :: GNU General Public License v3 (GPLv3)
Classifier: Operating System :: OS Independent
Requires-Python: >=3.7
License-File: LICENSE
Provides-Extra: all
Requires-Dist: black ; extra == 'all'
Requires-Dist: packaging ; extra == 'all'
Requires-Dist: pyflakes ; extra == 'all'
Requires-Dist: pylint ; extra == 'all'
Requires-Dist: requests ; extra == 'all'
Requires-Dist: twine ; extra == 'all'
Provides-Extra: dev
Requires-Dist: twine ; extra == 'dev'
Provides-Extra: test
Requires-Dist: black ; extra == 'test'
Requires-Dist: packaging ; extra == 'test'
Requires-Dist: pyflakes ; extra == 'test'
Requires-Dist: pylint ; extra == 'test'
Requires-Dist: requests ; extra == 'test'
